spktype21.py
spktype21-0.1.0.dist-info/LICENSE.txt
spktype21-0.1.0.dist-info/METADATA
spktype21-0.1.0.dist-info/WHEEL
spktype21-0.1.0.dist-info/top_level.txt
spktype21-0.1.0.dist-info/RECORD
