Metadata-Version: 2.1
Name: spktype21
Version: 0.1.0
Summary: A supporting module for jplephem to handle data type 21
Home-page: https://github.com/whiskie14142/spktype21
Author: whiskie14142
Author-email: whiskie14142@gmail.com
License: MIT
Keywords: jplephem SPK type21
Platform: UNKNOWN
Classifier: Development Status :: 4 - Beta
Classifier: Programming Language :: Python :: 3
Classifier: License :: OSI Approved :: MIT License
Classifier: Operating System :: OS Independent
